pytest_modifyscope/__init__.py
pytest_modifyscope-0.3.0.dist-info/LICENSE
pytest_modifyscope-0.3.0.dist-info/METADATA
pytest_modifyscope-0.3.0.dist-info/WHEEL
pytest_modifyscope-0.3.0.dist-info/entry_points.txt
pytest_modifyscope-0.3.0.dist-info/top_level.txt
pytest_modifyscope-0.3.0.dist-info/RECORD
