Metadata-Version: 2.1
Name: pytest-modifyscope
Version: 0.3.0
Summary: pytest plugin to modify fixture scope
Home-page: https://github.com/shungiku/pytest-modifyscope
Author: Shungiku
Author-email: shungiku@x06.org
License: UNKNOWN
Platform: UNKNOWN
Requires-Dist: pytest
